{
    "sessions": [
        {
            "sessionId": "scene_base_20260604_190542",
            "scenario": "scene_base",
            "startedAtUtc": "2026-06-04T19:05:42.2730000Z",
            "endedAtUtc": "2026-06-04T19:12:28.7190000Z",
            "durationSeconds": 406.4460144042969,
            "appUptimeAtSessionStartSeconds": 4.099999904632568,
            "appUptimeAtSessionEndSeconds": 410.5459899902344,
            "sampleCount": 83,
            "averageFps": 21.57571029663086,
            "averageFrameMs": 2369.602783203125,
            "worstFrameMs": 87698.9921875,
            "lowestSampledFps": 0.01140263956040144,
            "averageHeapMb": 13.662651062011719,
            "peakHeapMb": 15,
            "averageAllocatedMemoryMb": 109.0,
            "peakAllocatedMemoryMb": 109,
            "averageReservedMemoryMb": 118.9277114868164,
            "peakReservedMemoryMb": 119,
            "screenWidth": 1280,
            "screenHeight": 1808,
            "screenDpi": 192.0,
            "platform": "WebGLPlayer",
            "deviceType": "Desktop",
            "deviceModel": "Chrome 91.0.4472.134",
            "operatingSystem": "Android 12",
            "browserUrl": "https://delarge95.github.io/WebGL-Thesis-Proposal/Build/index.html",
            "unityVersion": "6000.4.3f1",
            "appVersion": "1.0",
            "sceneName": "MainScene_Final",
            "qualityLevel": "Low",
            "renderScale": 0.8500000238418579,
            "graphicsDeviceName": "Adreno (TM) 650",
            "graphicsDeviceType": "OpenGLES3",
            "systemMemoryMb": 276,
            "graphicsMemoryMb": 512,
            "viewMode": "Realistic",
            "explosionFactor": 0.0,
            "crossSectionEnabled": false,
            "rendererCount": 252,
            "enabledRendererCount": 252,
            "meshCount": 252,
            "estimatedTriangleCount": 229054
        }
    ]
}